django_datatables/__init__.py
django_datatables/admin.py
django_datatables/apps.py
django_datatables/colour_rows.py
django_datatables/columns.py
django_datatables/datatables.py
django_datatables/detect_device.py
django_datatables/filters.py
django_datatables/helpers.py
django_datatables/includes.py
django_datatables/modals.py
django_datatables/model_def.py
django_datatables/models.py
django_datatables/reorder_datatable.py
django_datatables/row_process.py
django_datatables/urls.py
django_datatables/widgets.py
django_datatables/migrations/0001_initial.py
django_datatables/migrations/__init__.py
django_datatables/plugins/__init__.py
django_datatables/plugins/colour_rows.py
django_datatables/plugins/column_totals.py
django_datatables/plugins/reorder.py
django_datatables/plugins/save_filters.py
django_datatables/static/django_datatables/css/datatables.css
django_datatables/static/django_datatables/js/filtered-datatable.js
django_datatables/static/django_datatables/js/filtered_datatables_legacy.js
django_datatables/static/django_datatables/js/legacy2.js
django_datatables/static/django_datatables/js/legacy3.js
django_datatables/static/django_datatables/js/runtime.js
django_datatables/templates/datatables/clear_table.html
django_datatables/templates/datatables/horizontal_table.html
django_datatables/templates/datatables/no_of_results.html
django_datatables/templates/datatables/no_of_rows.html
django_datatables/templates/datatables/search_boxes.html
django_datatables/templates/datatables/table.html
django_datatables/templates/datatables/table1.html
django_datatables/templates/datatables/filter_blocks/base_filter_block.html
django_datatables/templates/datatables/filter_blocks/date_filter.html
django_datatables/templates/datatables/filter_blocks/filter_control.html
django_datatables/templates/datatables/filter_blocks/pivot_filter.html
django_datatables/templates/datatables/filter_blocks/pivot_totals.html
django_filtered_datatables-0.0.21.dist-info/LICENSE
django_filtered_datatables-0.0.21.dist-info/METADATA
django_filtered_datatables-0.0.21.dist-info/WHEEL
django_filtered_datatables-0.0.21.dist-info/top_level.txt
django_filtered_datatables-0.0.21.dist-info/RECORD
