Metadata-Version: 2.1
Name: django-filtered-datatables
Version: 0.0.21
Summary: Django views with javascript filters using Datatables
Home-page: https://github.com/jonesim/django-datatables
Author: Ian Jones
License: UNKNOWN
Platform: UNKNOWN
Classifier: Programming Language :: Python :: 3
Classifier: License :: OSI Approved :: MIT License
Classifier: Operating System :: OS Independent
Requires-Python: >=3.6
Requires-Dist: django-ajax-helpers (>=0.0.16)
